LICENSE
MANIFEST.in
README.md
README.rst
setup.py
NanoLyse.egg-info/PKG-INFO
NanoLyse.egg-info/SOURCES.txt
NanoLyse.egg-info/dependency_links.txt
NanoLyse.egg-info/entry_points.txt
NanoLyse.egg-info/requires.txt
NanoLyse.egg-info/top_level.txt
nanolyse/NanoLyse.py
nanolyse/__init__.py
nanolyse/version.py
reference/DNA_CS.fasta
reference/lambda.fasta.gz