Metadata-Version: 2.1
Name: NanoLyse
Version: 1.2.1
Summary: Removing reads mapping to the lambda genome
Home-page: https://github.com/wdecoster/nanolyse
Author: Wouter De Coster
Author-email: decosterwouter@gmail.com
License: GPLv3
Keywords: nanopore sequencing processing
Classifier: Development Status :: 4 - Beta
Classifier: Intended Audience :: Science/Research
Classifier: Topic :: Scientific/Engineering :: Bio-Informatics
Classifier: License :: OSI Approved :: GNU General Public License v3 (GPLv3)
Classifier: Programming Language :: Python :: 3
Classifier: Programming Language :: Python :: 3.3
Classifier: Programming Language :: Python :: 3.4
Classifier: Programming Language :: Python :: 3.5
Requires-Python: >=3
License-File: LICENSE
